matchescu/py.typed
matchescu/reference_store/__init__.py
matchescu/reference_store/_exceptions.py
matchescu/reference_store/comparison_space/__init__.py
matchescu/reference_store/comparison_space/_in_memory.py
matchescu/reference_store/comparison_space/_protocol.py
matchescu/reference_store/id_table/__init__.py
matchescu/reference_store/id_table/_in_memory.py
matchescu/reference_store/id_table/_protocol.py
matchescu_reference_store-0.8.3.dist-info/LICENSE
matchescu_reference_store-0.8.3.dist-info/METADATA
matchescu_reference_store-0.8.3.dist-info/WHEEL
matchescu_reference_store-0.8.3.dist-info/RECORD
