Metadata-Version: 2.1
Name: matchescu-reference-store
Version: 0.8.3
Summary: Entity reference storage data types and APIs
License: MIT
Author: Andrei Olar
Author-email: andrei.olar@samlex.ro
Requires-Python: >=3.12,<4.0
Classifier: License :: OSI Approved :: MIT License
Classifier: Programming Language :: Python :: 3
Classifier: Programming Language :: Python :: 3.12
Classifier: Programming Language :: Python :: 3.13
Requires-Dist: matchescu-base (>=0.22.1,<0.23.0)
